nett_tv_nom.py
setup.cfg
setup.py
nett_tv_nom.egg-info/PKG-INFO
nett_tv_nom.egg-info/SOURCES.txt
nett_tv_nom.egg-info/dependency_links.txt
nett_tv_nom.egg-info/entry_points.txt
nett_tv_nom.egg-info/requires.txt
nett_tv_nom.egg-info/top_level.txt