Metadata-Version: 1.1
Name: nett-tv-nom
Version: 1.0.1
Summary: A simple python script for playing video from nrk nett-tv using media players such as vlc.
Home-page: https://github.com/bendikro/nett-tv-nom
Author: UNKNOWN
Author-email: UNKNOWN
License: BSD
Platform: UNKNOWN
Classifier: Programming Language :: Python :: 2.7
Classifier: Programming Language :: Python :: 3
Classifier: Development Status :: 4 - Beta
Classifier: License :: OSI Approved :: BSD License
Classifier: Natural Language :: English
Classifier: Operating System :: POSIX
